datasette_chatgpt_plugin/__init__.py
datasette_chatgpt_plugin-0.1.dist-info/LICENSE
datasette_chatgpt_plugin-0.1.dist-info/METADATA
datasette_chatgpt_plugin-0.1.dist-info/WHEEL
datasette_chatgpt_plugin-0.1.dist-info/entry_points.txt
datasette_chatgpt_plugin-0.1.dist-info/top_level.txt
datasette_chatgpt_plugin-0.1.dist-info/RECORD
