Metadata-Version: 2.1
Name: datasette-chatgpt-plugin
Version: 0.1
Summary: A Datasette plugin that turns a Datasette instance into a ChatGPT plugin
Home-page: https://github.com/simonw/datasette-chatgpt-plugin
Author: Simon Willison
License: Apache License, Version 2.0
Project-URL: Issues, https://github.com/simonw/datasette-chatgpt-plugin/issues
Project-URL: CI, https://github.com/simonw/datasette-chatgpt-plugin/actions
Project-URL: Changelog, https://github.com/simonw/datasette-chatgpt-plugin/releases
Classifier: Framework :: Datasette
Classifier: License :: OSI Approved :: Apache Software License
Requires-Python: >=3.7
License-File: LICENSE
Requires-Dist: datasette
Provides-Extra: test
Requires-Dist: pytest ; extra == 'test'
Requires-Dist: pytest-asyncio ; extra == 'test'
